pylsp_path_patcher/__init__.py
pylsp_path_patcher/plugin.py
pylsp_path_patcher-0.1.3.dist-info/LICENSE
pylsp_path_patcher-0.1.3.dist-info/METADATA
pylsp_path_patcher-0.1.3.dist-info/WHEEL
pylsp_path_patcher-0.1.3.dist-info/entry_points.txt
pylsp_path_patcher-0.1.3.dist-info/top_level.txt
pylsp_path_patcher-0.1.3.dist-info/RECORD
